{
  "content": [
    {
      "content": null,
      "created": "2021-09-08T07:40:44.253187Z",
      "format": null,
      "last_modified": "2021-09-08T07:40:44.253187Z",
      "mimetype": null,
      "name": "nb",
      "path": "nb",
      "size": null,
      "type": "directory",
      "writable": true
    }
  ],
  "created": "2021-09-08T07:40:44.209186Z",
  "format": "json",
  "last_modified": "2021-09-08T07:40:44.209186Z",
  "mimetype": null,
  "name": "",
  "path": "",
  "size": null,
  "type": "directory",
  "writable": true
}