{
  "content": [
    {
      "content": null,
      "created": "2021-12-28T14:02:12.870190Z",
      "format": null,
      "last_modified": "2021-12-28T14:02:12.870190Z",
      "mimetype": null,
      "name": "optimisation",
      "path": "nb/optimisation",
      "size": null,
      "type": "directory",
      "writable": true
    },
    {
      "content": null,
      "created": "2021-12-28T14:02:12.846189Z",
      "format": null,
      "last_modified": "2021-12-28T14:02:12.846189Z",
      "mimetype": null,
      "name": "image_processing",
      "path": "nb/image_processing",
      "size": null,
      "type": "directory",
      "writable": true
    },
    {
      "content": null,
      "created": "2021-12-28T14:02:12.866190Z",
      "format": null,
      "last_modified": "2021-12-28T14:02:12.866190Z",
      "mimetype": null,
      "name": "machine_learning",
      "path": "nb/machine_learning",
      "size": null,
      "type": "directory",
      "writable": true
    },
    {
      "content": null,
      "created": "2021-12-28T14:02:12.838189Z",
      "format": null,
      "last_modified": "2021-12-28T14:02:12.838189Z",
      "mimetype": null,
      "name": "deep_learning",
      "path": "nb/deep_learning",
      "size": null,
      "type": "directory",
      "writable": true
    }
  ],
  "created": "2021-12-28T14:02:12.866190Z",
  "format": "json",
  "last_modified": "2021-12-28T14:02:12.866190Z",
  "mimetype": null,
  "name": "nb",
  "path": "nb",
  "size": null,
  "type": "directory",
  "writable": true
}